{"account":{"acct":"brozek","avatar":"https://cdn.fosstodon.org/accounts/avatars/108/219/415/927/856/966/original/bae9f46f23936e79.jpg","display_name":"Brandon Rozek","header":"https://fosstodon.org/headers/original/missing.png","hide_collections":false,"id":"108219415927856966","indexable":false,"uri":"https://fosstodon.org/users/brozek","url":"https://fosstodon.org/@brozek","username":"brozek"},"application":{"name":"Tusky","website":"https://tusky.app"},"card":{"author_name":"","author_url":"","authors":[{"account":null,"name":"","url":""}],"blurhash":"U5SPX_%M?b004UfjxuIU?bRjIU-;M{-;M{Rj","description":"Life’s constraints may be simple, but life’s objectives are irreducibly complex.","embed_url":"","height":0,"html":"","image":null,"image_description":"","language":"en","provider_name":"Math with Bad Drawings","provider_url":"","published_at":null,"title":"Optimizing your life without losing your soul.","type":"link","url":"https://mathwithbaddrawings.com/2022/05/03/optimizing-your-life-without-losing-your-soul/","width":0},"content":"<p>Great post from Ben Orlin on treating time as a constraint and not an optimization target.</p><p>Example from his post: Instead of what is the fastest meal I can make, consider what’s the best meal I can make in the next 40 minutes?</p><p>:blobcatcookienom:  <a href=\"https://fosstodon.org/tags/lifehack\" class=\"mention hashtag\" rel=\"tag\">#<span>lifehack</span></a></p><p><a href=\"https://mathwithbaddrawings.com/2022/05/03/optimizing-your-life-without-losing-your-soul/\" target=\"_blank\" rel=\"nofollow noopener noreferrer\" translate=\"no\"><span class=\"invisible\">https://</span><span class=\"ellipsis\">mathwithbaddrawings.com/2022/0</span><span class=\"invisible\">5/03/optimizing-your-life-without-losing-your-soul/</span></a></p>","date":"2022-05-05T01:22:35.446Z","edited_at":null,"emojis":[{"shortcode":"blobcatcookienom","static_url":"https://cdn.fosstodon.org/custom_emojis/images/000/215/043/static/044816f9150cbdf7.png","url":"https://cdn.fosstodon.org/custom_emojis/images/000/215/043/original/044816f9150cbdf7.png","visible_in_picker":true}],"favourites_count":3,"id":"108246712676495736","in_reply_to_account_id":null,"in_reply_to_id":null,"language":"en","media_attachments":[],"mentions":[],"poll":null,"reblog":null,"reblogs_count":0,"replies_count":1,"sensitive":false,"spoiler_text":"","syndication":"https://fosstodon.org/@brozek/108246712676495736","tags":[{"name":"lifehack","url":"https://fosstodon.org/tags/lifehack"}],"visibility":"public"}