{"account":{"acct":"brozek","avatar":"https://cdn.fosstodon.org/accounts/avatars/108/219/415/927/856/966/original/bae9f46f23936e79.jpg","display_name":"Brandon Rozek","header":"https://fosstodon.org/headers/original/missing.png","hide_collections":false,"id":"108219415927856966","indexable":false,"uri":"https://fosstodon.org/users/brozek","url":"https://fosstodon.org/@brozek","username":"brozek"},"application":{"name":"Tusky","website":"https://tusky.app"},"card":null,"content":"<p><span class=\"h-card\" translate=\"no\"><a href=\"https://fosstodon.org/@benjaminhollon\" class=\"u-url mention\">@<span>benjaminhollon</span></a></span> Out of curiosity, which color did you end up choosing for your poster?</p>","date":"2022-05-20T14:49:25.847Z","edited_at":null,"emojis":[],"favourites_count":0,"id":"108334819957156585","in_reply_to_account_id":"107465786468503157","in_reply_to_id":"108301021814358610","language":"en","media_attachments":[],"mentions":[{"acct":"benjaminhollon","id":"107465786468503157","url":"https://fosstodon.org/@benjaminhollon","username":"benjaminhollon"}],"poll":null,"reblog":null,"reblogs_count":0,"replies_count":1,"sensitive":false,"spoiler_text":"","syndication":"https://fosstodon.org/@brozek/108334819957156585","tags":[],"visibility":"unlisted"}